introductie/__init__.py
introductie/app.py
introductie-0.1.4.dist-info/WHEEL
introductie-0.1.4.dist-info/METADATA
introductie-0.1.4.dist-info/RECORD
