Metadata-Version: 2.1
Name: introductie
Version: 0.1.4
Summary: 
Author: Dennis van Bohemen
Author-email: Dennis.Van.Bohemen@topicus.nl
Requires-Python: >=3.7,<4.0
Classifier: Programming Language :: Python :: 3
Classifier: Programming Language :: Python :: 3.7
Classifier: Programming Language :: Python :: 3.8
Classifier: Programming Language :: Python :: 3.9
Requires-Dist: namen (>=0.4.0,<0.5.0)
